[
	{
		"__TYPE__": "SharedSliceContent",
		"variation": "default",
		"primary": {
			"is_active": {
				"__TYPE__": "BooleanContent",
				"value": false
			},
			"image_desktop": {
				"origin": {
					"id": "main",
					"url": "https://images.unsplash.com/photo-1494173853739-c21f58b16055",
					"width": 3277,
					"height": 4092
				},
				"url": "https://images.unsplash.com/photo-1494173853739-c21f58b16055",
				"width": 3277,
				"height": 4092,
				"edit": {
					"zoom": 1,
					"crop": {
						"x": 0,
						"y": 0
					},
					"background": "transparent"
				},
				"credits": null,
				"alt": null,
				"__TYPE__": "ImageContent",
				"thumbnails": {}
			},
			"image_mobile": {
				"origin": {
					"id": "main",
					"url": "https://images.unsplash.com/photo-1601933973783-43cf8a7d4c5f",
					"width": 6597,
					"height": 4398
				},
				"url": "https://images.unsplash.com/photo-1601933973783-43cf8a7d4c5f",
				"width": 6597,
				"height": 4398,
				"edit": {
					"zoom": 1,
					"crop": {
						"x": 0,
						"y": 0
					},
					"background": "transparent"
				},
				"credits": null,
				"alt": null,
				"__TYPE__": "ImageContent",
				"thumbnails": {}
			},
			"image_link": {
				"__TYPE__": "LinkContent",
				"value": {
					"__TYPE__": "ExternalLink",
					"url": "https://prismic.io"
				}
			}
		},
		"items": []
	}
]